[{"name":"orchid","displayName":"Orchid","hexCode":"#DA70D6"},{"name":"pink","displayName":"Pink","hexCode":"#ffc0cb"},{"name":"limegreen","displayName":"Lime green","hexCode":"#32cd32"},{"name":"peachpuff","displayName":"Peach","hexCode":"#ffdab9"},{"name":"red","displayName":"Red","hexCode":"#ff0000"},{"name":"teal","displayName":"Teal","hexCode":"#008080"},{"name":"green","displayName":"Green","hexCode":"#008000"},{"name":"yellow","displayName":"Yellow","hexCode":"#ffff00"},{"name":"gray","displayName":"Gray","hexCode":"#808080"},{"name":"violet","displayName":"Violet","hexCode":"#ee82ee"},{"name":"orange","displayName":"Orange","hexCode":"#ffa500"},{"name":"white","displayName":"White","hexCode":"#ffffff"},{"name":"gold","displayName":"Gold","hexCode":"#ffd700"},{"name":"black","displayName":"Black","hexCode":"#000000"},{"name":"brown","displayName":"Brown","hexCode":"#a52a2a"},{"name":"darkred","displayName":"Dark Red","hexCode":"#8b0000"},{"name":"purple","displayName":"Purple","hexCode":"#800080"},{"name":"lavender","displayName":"Lavender","hexCode":"#e6e6fa"},{"name":"turquoise","displayName":"Turquoise","hexCode":"#40e0d0"},{"name":"blue","displayName":"Blue","hexCode":"#0000ff"},{"name":"whitesmoke","displayName":"Pearl","hexCode":"#f5f5f5"},{"name":"silver","displayName":"Silver","hexCode":"#c0c0c0"},{"name":"navy","displayName":"Navy","hexCode":"#000080"},{"name":"lightblue","displayName":"Light Blue","hexCode":"#add8e6"},{"name":"ivory","displayName":"Ivory","hexCode":"#fffff0"}]